Metadata-Version: 2.1
Name: Random-Spanish-Words
Version: 0.0.1
Summary: Libreria para obtener palabras o listas de palabras en Español de forma aleatoria
Home-page: https://github.com/08wwwxxxwww80
Author: Reydel Romeu Alonso
Author-email: reydelromeu@gmail.com
License: MIT
Platform: UNKNOWN
